LICENSE
README.md
setup.py
vorlang_polish.egg-info/PKG-INFO
vorlang_polish.egg-info/SOURCES.txt
vorlang_polish.egg-info/dependency_links.txt
vorlang_polish.egg-info/top_level.txt
vorlangpolish/__init__.py
vorlangpolish/format.py