Metadata-Version: 2.1
Name: vorlang-polish
Version: 0.0.2
Summary: The VOR Programming Language Polisher
Author: Vorlang
Author-email: me@zanderlewis.dev
Classifier: Programming Language :: Python :: 3
Classifier: License :: OSI Approved :: MIT License
Classifier: Operating System :: OS Independent
Requires-Python: >=3.6
License-File: LICENSE
